<?xml version="1.0" encoding="utf-8"?>
<Dialogue name="Finz">


<SpeechNode text="Aeona!" name="Finz1">
<Option text="What!  What? Finz!?"/>
<Option text="Not now FinnzyBoy!"/>
</SpeechNode>

<SpeechNode text="Discovered!  JEWELZ.. in forest! Bright!  Beautiful!  Make me happy!" name="Finz2">
<Option text="Where Finz?  Where is it?"/>
</SpeechNode>

<SpeechNode text="I forget! Bye Bye!"name="Finz3">
</SpeechNode>

<SpeechNode text="But! But!... JEWELZ!"name="FinzA">
</SpeechNode>

<Connection speechA="Finz1" option="1" speechB="Finz2"/>
<Connection speechA="Finz1" option="2" speechB="FinzA"/>

<Connection speechA="Finz2" option="1" speechB="Finz3"/>

</Dialogue>



